MANIFEST.in
README.rst
setup.py
src/zyzz/__init__.py
src/zyzz/breakin.py
src/zyzz/encode_output.py
src/zyzz/global_lock.py
src/zyzz.egg-info/PKG-INFO
src/zyzz.egg-info/SOURCES.txt
src/zyzz.egg-info/dependency_links.txt
src/zyzz.egg-info/top_level.txt