Metadata-Version: 1.1
Name: zyzz
Version: 1.0.1
Summary: Python util modules
Home-page: http://github.com/nailgun/zyzz/
Author: Dmitry Bashkatov
Author-email: dbashkatov@gmail.com
License: UNKNOWN
Platform: UNKNOWN
Classifier: Development Status :: 4 - Beta
Classifier: Environment :: Console
Classifier: Intended Audience :: Developers
Classifier: License :: OSI Approved :: MIT License
Classifier: Topic :: Utilities
